Workbook

Sheet Principais Transações
A3: PS | B3: Liquidação total de projetos qdo aplicável | C3: CJ88
A4: AA | B4: Lançar depreciação | C4: AFAB
A6: FI-AP | B6: Emissão de relatório de partidas em aberto - em 31/05 | C6: FBL1N
A7: FI-AR | B7: Emissão de relatório de partidas em aberto - em 31/05 | C7: FBL5N
A9: AR/AP | B9: Atualizar taxas de conversão de moeda | C9: OB08
A11: MM | B11: Diferir período para abertura do mês seguinte | C11: MMPV | D11: Duda
A12: FI | B12: Abrir novo período contábil | C12: OB52 | D12: S_ALR_87003642
A14: FI-GL | B14: Efetuar compensação de contas | C14: F.19
A16: FI-GL | B16: Avaliação em moeda estrangeira | C16: F.05 | D16: FAGL_FC_VAL
A18: FI-GL | B18: Bloquear períodos contábeis | C18: OB52
B20: P&L - Preliminar Gerar Summary | C20: GRR3

Sheet CAMINHOES (2)
B5: CRONOGRAMA FECHAMENTO - JANEIRO
B7: Nº | C7: ATIVIDADES | D7: AREA | E7: Responsavel | F7: Dia Maximo | G7: Horario Maximo | I7: Entregue em | J7: Horário entrega | L7: Integração Contabil | M7: Responsavel | N7: Status
B8: 1 | C8: Folha de Pagamento | D8: DP | E8: Marta/ Elizete | F8: 3° dia util | G8: 0.75
B10: 2 | C10: Compras | D10: Suprimentos | E10: Marcus/ Leânia | F10: 5° dia util | G10: 0.75
B12: 3 | C12: Vendas | D12: Faturamento | E12: Marcus/ Fabiana | F12: 3° dia util | G12: 0.75
B14: 4 | C14: Estoque | D14: Estoque | F14: 3° dia util | G14: 0.75
B16: 5 | C16: Contas a Pagar | D16: Financeiro | F16: 3° dia util | G16: 0.75
B18: 6 | C18: Contas a Receber | D18: Financeiro | F18: 3° dia util | G18: 0.75
B20: 7 | C20: Tesouraria | D20: Financeiro | F20: 3° dia util | G20: 0.75
B22: 8 | C22: Patrimômio (movimentação) | D22: Patrimonio | F22: 3° dia util | G22: 0.75
B24: 9 | C24: Tributos | D24: Fiscal | F24: 3° dia util | G24: 0.75
B26: * A GERENCIA DE CADA ÁREA DEVERÁ GARANTIR O FECHAMENTO DO CRONOGRAMA NOS DIAS E HORÁRIOS FIXADOS

Sheet Resumo
B3: ='Consolidado- Comber'!B5 -> CRONOGRAMA FECHAMENTO - SETEMBRO 2026
C4: Atividade | D4: responsável | E4: Data Final
B7: Contábil | C7: Contábil/Integração | D7: Iviane/ Equipe Contábil | E7: 12º dia útil - 19/jan
C8: Balancete Fechado | D8: Iviane/ Equipe Contábil | E8: 5º dia útil - 08/jan
B9: DP | C9: Folha de Pagamento | D9: Marta/ Elizete | E9: 3º dia útil - 06/jan
B10: Estoque | C10: Estoque | D10: Marcus | E10: 2º dia útil - 05/jan
B11: Faturamento | C11: Vendas | D11: Marcus/ Fabiana | E11: 2º dia útil - 05/jan
B12: Financeiro | C12: Contas a Pagar | D12: Patricia/ Walis/ Beatriz | E12: 3º dia útil - 06/jan
C13: Contas a Receber | D13: Patricia/ Thaynara | E13: 3º dia útil - 06/jan
C14: Tesouraria | D14: Patricia/ Regicléssia | E14: 3º dia útil - 06/jan
B15: Fiscal | C15: Tributos | D15: Iviane | E15: 4º dia útil - 07/jan
B16: Patrimonio | C16: Patrimômio (movimentação) | D16: Juíra/ Guilherme | E16: 3º dia útil - 06/jan
B17: Suprimentos | C17: Compras | D17: Marcus/ Leânia | E17: 2º dia útil - 05/jan
B18: Total Geral

Sheet Resumo2
B3: AREA | C3: ATIVIDADES | D3: Responsavel | E3: Dia Maximo | F3: D.U
B4: Contábil | C4: Balancete Fechado | D4: Iviane/ Equipe Contábil | E4: 16º dia útil - 23/mar | F4: 16
B5: Contábil | C5: Contábil/Integração | D5: Iviane/ Equipe Contábil | E5: 5º dia útil - 06/mar | F5: 5
B6: DP | C6: Folha de Pagamento | D6: Marta/ Elizete | E6: 4º dia útil - 05/mar | F6: 4
B7: Estoque | C7: Estoque | D7: Marcus | E7: 1º dia útil - 02/mar | F7: 1
B8: Faturamento | C8: Vendas | D8: Marcus/ Fabiana | E8: 1º dia útil - 02/mar | F8: 1
B9: Financeiro | C9: Contas a Pagar | D9: Patricia/ Walis | E9: 2º dia útil - 03/mar | F9: 2
B10: Financeiro | C10: Contas a Receber | D10: Patricia/ Thaynara | E10: 2º dia útil - 03/mar | F10: 2
B11: Financeiro | C11: Contas a Receber | D11: Patricia/ Luciene | E11: 2º dia útil - 03/mar | F11: 2
B12: Financeiro | C12: Contas a Receber | D12: Patricia/Luciene | E12: 2º dia útil - 03/mar | F12: 2
B13: Financeiro | C13: Tesouraria | D13: Patricia/ Regicléssia | E13: 2º dia útil - 03/mar | F13: 2
B14: Fiscal | C14: Tributos | D14: Iviane | E14: 3º dia útil - 04/mar | F14: 3
B15: Patrimonio | C15: Patrimômio (movimentação) | D15: Kaio/ Gabriely | E15: 2º dia útil - 03/mar | F15: 2
B16: Suprimentos | C16: Compras | D16: Marcus/ Leânia | E16: 1º dia útil - 02/mar | F16: 1
B18: AREA | C18: ATIVIDADES | D18: RESPONSÁVEL | E18: DIA MÁXIMO | F18: D.U
B19: Estoque | C19: Estoque | D19: Marcus | E19: 1º dia útil - 02/mar | F19: =_xlfn.XLOOKUP(C19,$C$4:$C$16,$F$4:$F$16,0,0) -> 1 | I19: =_xlfn.XLOOKUP(G19,$C$4:$C$16,$E$4:$E$16,0,0) -> 0
B20: Faturamento | C20: Vendas | D20: Marcus/ Fabiana | E20: 1º dia útil - 02/mar | F20: =_xlfn.XLOOKUP(C20,$C$4:$C$16,$F$4:$F$16,0,0) -> 1
B21: Suprimentos | C21: Compras | D21: Marcus/ Leânia | E21: 1º dia útil - 02/mar | F21: =_xlfn.XLOOKUP(C21,$C$4:$C$16,$F$4:$F$16,0,0) -> 1
B22: Financeiro | C22: Contas a Pagar | D22: Patricia/ Walis | E22: 2º dia útil - 03/mar | F22: =_xlfn.XLOOKUP(C22,$C$4:$C$16,$F$4:$F$16,0,0) -> 2
B23: Financeiro | C23: Contas a Receber | D23: Patricia/ Thaynara | E23: 2º dia útil - 03/mar | F23: =_xlfn.XLOOKUP(C23,$C$4:$C$16,$F$4:$F$16,0,0) -> 2
B24: Financeiro | C24: Contas a Receber | D24: Patricia/ Luciene | E24: 2º dia útil - 03/mar | F24: =_xlfn.XLOOKUP(C24,$C$4:$C$16,$F$4:$F$16,0,0) -> 2
B25: Financeiro | C25: Contas a Receber | D25: Patricia/Luciene | E25: 2º dia útil - 03/mar | F25: =_xlfn.XLOOKUP(C25,$C$4:$C$16,$F$4:$F$16,0,0) -> 2
B26: Financeiro | C26: Tesouraria | D26: Patricia/ Regicléssia | E26: 2º dia útil - 03/mar | F26: =_xlfn.XLOOKUP(C26,$C$4:$C$16,$F$4:$F$16,0,0) -> 2
B27: Patrimonio | C27: Patrimômio (movimentação) | D27: Kaio/ Gabriely | E27: 2º dia útil - 03/mar | F27: =_xlfn.XLOOKUP(C27,$C$4:$C$16,$F$4:$F$16,0,0) -> 2
B28: Fiscal | C28: Tributos | D28: Iviane | E28: 3º dia útil - 04/mar | F28: =_xlfn.XLOOKUP(C28,$C$4:$C$16,$F$4:$F$16,0,0) -> 3
B29: DP | C29: Folha de Pagamento | D29: Marta/ Elizete | E29: 4º dia útil - 05/mar | F29: =_xlfn.XLOOKUP(C29,$C$4:$C$16,$F$4:$F$16,0,0) -> 4
B30: Contábil | C30: Contábil/Integração | D30: Iviane/ Equipe Contábil | E30: 5º dia útil - 06/mar | F30: =_xlfn.XLOOKUP(C30,$C$4:$C$16,$F$4:$F$16,0,0) -> 5
B31: Contábil | C31: Balancete Fechado | D31: Iviane/ Equipe Contábil | E31: 16º dia útil - 23/mar | F31: =_xlfn.XLOOKUP(C31,$C$4:$C$16,$F$4:$F$16,0,0) -> 16

Sheet Planilha1
A1: Entregue em | B1: (vazio)
A2: Dia Maximo | B2: (Vários itens)
A4: Rótulos de Linha
A5: Contábil
A6: Contábil/Integração
A7: Iviane/ Equipe Contábil
A8: DP
A9: Folha de Pagamento
A10: Marta/ Elizete
A11: Estoque
A12: Estoque
A13: Marcus
A14: Faturamento
A15: Vendas
... A34: Total Geral

Sheet Consolidado- Comber
A1: =TEXT(_xlfn.TEXTAFTER(B5,"- "),"m")+1 -> 10
E3: * A GERENCIA DE CADA ÁREA DEVERÁ GARANTIR O FECHAMENTO DO CRONOGRAMA NOS DIAS E HORÁRIOS PREVISTOS
B5: CRONOGRAMA FECHAMENTO - SETEMBRO 2026
B7: Nº | C7: Empresa | D7: ATIVIDADES | E7: AREA | F7: Responsavel | G7: Dia Maximo | H7: Horario Maximo | I7: x | J7: Entregue em | K7: Horário entrega | L7: x | M7: Obs | N7: x | O7: D.U
B8: 1 | C8: LOGISTICA | D8: Folha de Pagamento | E8: DP | F8: Marta/ Elizete | G8: =$O8&"º dia útil - "&TEXT(_xlfn.XLOOKUP($A$1&"|"&$O8,ListBox!$H:$H,ListBox!$A:$A,0,0),"DD/MMM") -> 4º dia útil - 06/out | H8: 0.75 | O8: 4
B9: 2 | C9: LOGISTICA | D9: Compras | E9: Suprimentos | F9: Kaio/Erica | G9: 46295 | H9: 0.75 | O9: 1
B10: 3 | C10: LOGISTICA | D10: Vendas | E10: Faturamento | F10: Marcus/ Fabiana | G10: 46295 | H10: 0.75 | O10: 1
B11: 1 | C11: LOGISTICA | D11: Folha de Pagamento | E11: DP | F11: Marta/ Elizete | G11: =$O11&"º dia útil - "&TEXT(_xlfn.XLOOKUP($A$1&"|"&$O11,ListBox!$H:$H,ListBox!$A:$A,0,0),"DD/MMM") -> 4º dia útil - 06/out | H11: 0.75 | O11: 4
B12: 2 | C12: LOGISTICA | D12: Compras | E12: Suprimentos | F12: Kaio/Erica | G12: 46295 | H12: 0.75 | O12: 1
B13: 3 | C13: LOGISTICA | D13: Vendas | E13: Faturamento | F13: Marcus/ Fabiana | G13: 46295 | H13: 0.75 | O13: 1
B14: 4 | C14: LOGISTICA | D14: Estoque | E14: Estoque | F14: Marcus | G14: 46295 | H14: 0.75 | O14: 1
B15: 5 | C15: LOGISTICA | D15: Contas a Pagar | E15: Financeiro | F15: Patricia/ Regiclessia | G15: =$O15&"º dia útil - "&TEXT(_xlfn.XLOOKUP($A$1&"|"&$O15,ListBox!$H:$H,ListBox!$A:$A,0,0),"DD/MMM") -> 3º dia útil - 05/out | H15: 0.75 | O15: 3
B16: 6 | C16: LOGISTICA | D16: Contas a Receber | E16: Financeiro | F16: Patricia/Luciene | G16: =$O16&"º dia útil - "&TEXT(_xlfn.XLOOKUP($A$1&"|"&$O16,ListBox!$H:$H,ListBox!$A:$A,0,0),"DD/MMM") -> 3º dia útil - 05/out | H16: 0.75 | O16: 3
B17: 7 | C17: LOGISTICA | D17: Tesouraria | E17: Financeiro | F17: Patricia/ Regicléssia | G17: =$O17&"º dia útil - "&TEXT(_xlfn.XLOOKUP($A$1&"|"&$O17,ListBox!$H:$H,ListBox!$A:$A,0,0),"DD/MMM") -> 3º dia útil - 05/out | H17: 0.75 | O17: 3
B18: 8 | C18: LOGISTICA | D18: Patrimômio (movimentação) | E18: Patrimonio | F18: Gabriely | G18: =$O18&"º dia útil - "&TEXT(_xlfn.XLOOKUP($A$1&"|"&$O18,ListBox!$H:$H,ListBox!$A:$A,0,0),"DD/MMM") -> 3º dia útil - 05/out | H18: 0.75 | O18: 3
B19: 9 | C19: LOGISTICA | D19: Tributos | E19: Fiscal | F19: Joyce | G19: =$O19&"º dia útil - "&TEXT(_xlfn.XLOOKUP($A$1&"|"&$O19,ListBox!$H:$H,ListBox!$A:$A,0,0),"DD/MMM") -> 7º dia útil - 09/out | H19: 0.75 | O19: 7
B20: 1 | C20: BIOMASSA | D20: Folha de Pagamento | E20: DP | F20: Marta/ Elizete | G20: =$O20&"º dia útil - "&TEXT(_xlfn.XLOOKUP($A$1&"|"&$O20,ListBox!$H:$H,ListBox!$A:$A,0,0),"DD/MMM") -> 4º dia útil - 06/out | H20: 0.75 | O20: 4
B21: 2 | C21: BIOMASSA | D21: Compras | E21: Suprimentos | F21: Kaio/Erica | G21: 46295 | H21: 0.75 | O21: 1
B22: 3 | C22: BIOMASSA | D22: Vendas | E22: Faturamento | F22: Marcus/ Fabiana | G22: 46295 | H22: 0.75 | O22: 1
B23: 1 | C23: BIOMASSA | D23: Folha de Pagamento | E23: DP | F23: Marta/ Elizete | G23: =$O23&"º dia útil - "&TEXT(_xlfn.XLOOKUP($A$1&"|"&$O23,ListBox!$H:$H,ListBox!$A:$A,0,0),"DD/MMM") -> 4º dia útil - 06/out | H23: 0.75 | O23: 4
B24: 2 | C24: BIOMASSA | D24: Compras | E24: Suprimentos | F24: Kaio/Erica | G24: 46295 | H24: 0.75 | O24: 1
B25: 3 | C25: BIOMASSA | D25: Vendas | E25: Faturamento | F25: Marcus/ Fabiana | G25: 46295 | H25: 0.75 | O25: 1
B26: 4 | C26: BIOMASSA | D26: Estoque | E26: Estoque | F26: Marcus | G26: 46295 | H26: 0.75 | O26: 1
B27: 5 | C27: BIOMASSA | D27: Contas a Pagar | E27: Financeiro | F27: Patricia/ Regiclessia | G27: =$O27&"º dia útil - "&TEXT(_xlfn.XLOOKUP($A$1&"|"&$O27,ListBox!$H:$H,ListBox!$A:$A,0,0),"DD/MMM") -> 3º dia útil - 05/out | H27: 0.75 | O27: 3
B28: 6 | C28: BIOMASSA | D28: Contas a Receber | E28: Financeiro | F28: Patricia/Luciene | G28: =$O28&"º dia útil - "&TEXT(_xlfn.XLOOKUP($A$1&"|"&$O28,ListBox!$H:$H,ListBox!$A:$A,0,0),"DD/MMM") -> 3º dia útil - 05/out | H28: 0.75 | O28: 3
B29: 7 | C29: BIOMASSA | D29: Tesouraria | E29: Financeiro | F29: Patricia/ Regicléssia | G29: =$O29&"º dia útil - "&TEXT(_xlfn.XLOOKUP($A$1&"|"&$O29,ListBox!$H:$H,ListBox!$A:$A,0,0),"DD/MMM") -> 3º dia útil - 05/out | H29: 0.75 | O29: 3
B30: 8 | C30: BIOMASSA | D30: Patrimômio (movimentação) | E30: Patrimonio | F30: Gabriely | G30: =$O30&"º dia útil - "&TEXT(_xlfn.XLOOKUP($A$1&"|"&$O30,ListBox!$H:$H,ListBox!$A:$A,0,0),"DD/MMM") -> 3º dia útil - 05/out | H30: 0.75 | O30: 3
B31: 9 | C31: BIOMASSA | D31: Tributos | E31: Fiscal | F31: Joyce | G31: =$O31&"º dia útil - "&TEXT(_xlfn.XLOOKUP($A$1&"|"&$O31,ListBox!$H:$H,ListBox!$A:$A,0,0),"DD/MMM") -> 7º dia útil - 09/out | H31: 0.75 | O31: 7
B32: 1 | C32: COMBER SA | D32: Folha de Pagamento | E32: DP | F32: Marta/ Elizete | G32: =$O32&"º dia útil - "&TEXT(_xlfn.XLOOKUP($A$1&"|"&$O32,ListBox!$H:$H,ListBox!$A:$A,0,0),"DD/MMM") -> 4º dia útil - 06/out | H32: 0.75 | O32: 4
B33: 2 | C33: COMBER SA | D33: Compras | E33: Suprimentos | F33: Kaio/Erica | G33: 46295 | H33: 0.75 | O33: 1
B34: 3 | C34: COMBER SA | D34: Vendas | E34: Faturamento | F34: Marcus/ Fabiana | G34: 46295 | H34: 0.75 | O34: 1
B35: 1 | C35: COMBER SA | D35: Folha de Pagamento | E35: DP | F35: Marta/ Elizete | G35: =$O35&"º dia útil - "&TEXT(_xlfn.XLOOKUP($A$1&"|"&$O35,ListBox!$H:$H,ListBox!$A:$A,0,0),"DD/MMM") -> 4º dia útil - 06/out | H35: 0.75 | O35: 4
B36: 2 | C36: COMBER SA | D36: Compras | E36: Suprimentos | F36: Kaio/Erica | G36: 46295 | H36: 0.75 | O36: 1
B37: 3 | C37: COMBER SA | D37: Vendas | E37: Faturamento | F37: Marcus/ Fabiana | G37: 46295 | H37: 0.75 | O37: 1
B38: 4 | C38: COMBER SA | D38: Estoque | E38: Estoque | F38: Marcus | G38: 46295 | H38: 0.75 | O38: 1
B39: 5 | C39: COMBER SA | D39: Contas a Pagar | E39: Financeiro | F39: Patricia/ Regiclessia | G39: =$O39&"º dia útil - "&TEXT(_xlfn.XLOOKUP($A$1&"|"&$O39,ListBox!$H:$H,ListBox!$A:$A,0,0),"DD/MMM") -> 3º dia útil - 05/out | H39: 0.75 | O39: 3
B40: 6 | C40: COMBER SA | D40: Contas a Receber | E40: Financeiro | F40: Patricia/Luciene | G40: =$O40&"º dia útil - "&TEXT(_xlfn.XLOOKUP($A$1&"|"&$O40,ListBox!$H:$H,ListBox!$A:$A,0,0),"DD/MMM") -> 3º dia útil - 05/out | H40: 0.75 | O40: 3
B41: 7 | C41: COMBER SA | D41: Tesouraria | E41: Financeiro | F41: Patricia/ Regicléssia | G41: =$O41&"º dia útil - "&TEXT(_xlfn.XLOOKUP($A$1&"|"&$O41,ListBox!$H:$H,ListBox!$A:$A,0,0),"DD/MMM") -> 3º dia útil - 05/out | H41: 0.75 | O41: 3
B42: 8 | C42: COMBER SA | D42: Patrimômio (movimentação) | E42: Patrimonio | F42: Gabriely | G42: =$O42&"º dia útil - "&TEXT(_xlfn.XLOOKUP($A$1&"|"&$O42,ListBox!$H:$H,ListBox!$A:$A,0,0),"DD/MMM") -> 3º dia útil - 05/out | H42: 0.75 | O42: 3
B43: 9 | C43: COMBER SA | D43: Tributos | E43: Fiscal | F43: Joyce | G43: =$O43&"º dia útil - "&TEXT(_xlfn.XLOOKUP($A$1&"|"&$O43,ListBox!$H:$H,ListBox!$A:$A,0,0),"DD/MMM") -> 7º dia útil - 09/out | H43: 0.75 | O43: 7
B44: 1 | C44: FLORESTAL TO | D44: Folha de Pagamento | E44: DP | F44: Marta/ Elizete | G44: =$O44&"º dia útil - "&TEXT(_xlfn.XLOOKUP($A$1&"|"&$O44,ListBox!$H:$H,ListBox!$A:$A,0,0),"DD/MMM") -> 4º dia útil - 06/out | H44: 0.75 | O44: 4
B45: 2 | C45: FLORESTAL TO | D45: Compras | E45: Suprimentos | F45: Kaio/Erica | G45: 46295 | H45: 0.75 | O45: 1
B46: 3 | C46: FLORESTAL TO | D46: Vendas | E46: Faturamento | F46: Marcus/ Fabiana | G46: 46295 | H46: 0.75 | O46: 1
B47: 1 | C47: FLORESTAL TO | D47: Folha de Pagamento | E47: DP | F47: Marta/ Elizete | G47: =$O47&"º dia útil - "&TEXT(_xlfn.XLOOKUP($A$1&"|"&$O47,ListBox!$H:$H,ListBox!$A:$A,0,0),"DD/MMM") -> 4º dia útil - 06/out | H47: 0.75 | O47: 4
B48: 2 | C48: FLORESTAL TO | D48: Compras | E48: Suprimentos | F48: Kaio/Erica | G48: 46295 | H48: 0.75 | O48: 1
B49: 3 | C49: FLORESTAL TO | D49: Vendas | E49: Faturamento | F49: Marcus/ Fabiana | G49: 46295 | H49: 0.75 | O49: 1
B50: 4 | C50: FLORESTAL TO | D50: Estoque | E50: Estoque | F50: Marcus | G50: 46295 | H50: 0.75 | O50: 1
B51: 5 | C51: FLORESTAL TO | D51: Contas a Pagar | E51: Financeiro | F51: Patricia/ Regiclessia | G51: =$O51&"º dia útil - "&TEXT(_xlfn.XLOOKUP($A$1&"|"&$O51,ListBox!$H:$H,ListBox!$A:$A,0,0),"DD/MMM") -> 3º dia útil - 05/out | H51: 0.75 | O51: 3
B52: 6 | C52: FLORESTAL TO | D52: Contas a Receber | E52: Financeiro | F52: Patricia/Luciene | G52: =$O52&"º dia útil - "&TEXT(_xlfn.XLOOKUP($A$1&"|"&$O52,ListBox!$H:$H,ListBox!$A:$A,0,0),"DD/MMM") -> 3º dia útil - 05/out | H52: 0.75 | O52: 3
B53: 7 | C53: FLORESTAL TO | D53: Tesouraria | E53: Financeiro | F53: Patricia/ Regicléssia | G53: =$O53&"º dia útil - "&TEXT(_xlfn.XLOOKUP($A$1&"|"&$O53,ListBox!$H:$H,ListBox!$A:$A,0,0),"DD/MMM") -> 3º dia útil - 05/out | H53: 0.75 | O53: 3
B54: 8 | C54: FLORESTAL TO | D54: Patrimômio (movimentação) | E54: Patrimonio | F54: Gabriely | G54: =$O54&"º dia útil - "&TEXT(_xlfn.XLOOKUP($A$1&"|"&$O54,ListBox!$H:$H,ListBox!$A:$A,0,0),"DD/MMM") -> 3º dia útil - 05/out | H54: 0.75 | O54: 3
B55: 9 | C55: FLORESTAL TO | D55: Tributos | E55: Fiscal | F55: Joyce | G55: =$O55&"º dia útil - "&TEXT(_xlfn.XLOOKUP($A$1&"|"&$O55,ListBox!$H:$H,ListBox!$A:$A,0,0),"DD/MMM") -> 7º dia útil - 09/out | H55: 0.75 | O55: 7
B56: 1 | C56: SEMINOVOS | D56: Folha de Pagamento | E56: DP | F56: Marta/ Elizete | G56: =$O56&"º dia útil - "&TEXT(_xlfn.XLOOKUP($A$1&"|"&$O56,ListBox!$H:$H,ListBox!$A:$A,0,0),"DD/MMM") -> 4º dia útil - 06/out | H56: 0.75 | O56: 4
B57: 2 | C57: SEMINOVOS | D57: Compras | E57: Suprimentos | F57: Kaio/Erica | G57: 46295 | H57: 0.75 | O57: 1
B58: 3 | C58: SEMINOVOS | D58: Vendas | E58: Faturamento | F58: Marcus/ Fabiana | G58: 46295 | H58: 0.75 | O58: 1
B59: 1 | C59: SEMINOVOS | D59: Folha de Pagamento | E59: DP | F59: Marta/ Elizete | G59: =$O59&"º dia útil - "&TEXT(_xlfn.XLOOKUP($A$1&"|"&$O59,ListBox!$H:$H,ListBox!$A:$A,0,0),"DD/MMM") -> 4º dia útil - 06/out | H59: 0.75 | O59: 4
B60: 2 | C60: SEMINOVOS | D60: Compras | E60: Suprimentos | F60: Kaio/Erica | G60: 46295 | H60: 0.75 | O60: 1
B61: 3 | C61: SEMINOVOS | D61: Vendas | E61: Faturamento | F61: Marcus/ Fabiana | G61: 46295 | H61: 0.75 | O61: 1
B62: 4 | C62: SEMINOVOS | D62: Estoque | E62: Estoque | F62: Marcus | G62: 46295 | H62: 0.75 | O62: 1
B63: 5 | C63: SEMINOVOS | D63: Contas a Pagar | E63: Financeiro | F63: Patricia/ Regiclessia | G63: =$O63&"º dia útil - "&TEXT(_xlfn.XLOOKUP($A$1&"|"&$O63,ListBox!$H:$H,ListBox!$A:$A,0,0),"DD/MMM") -> 3º dia útil - 05/out | H63: 0.75 | O63: 3
B64: 6 | C64: SEMINOVOS | D64: Contas a Receber | E64: Financeiro | F64: Patricia/Luciene | G64: =$O64&"º dia útil - "&TEXT(_xlfn.XLOOKUP($A$1&"|"&$O64,ListBox!$H:$H,ListBox!$A:$A,0,0),"DD/MMM") -> 3º dia útil - 05/out | H64: 0.75 | O64: 3
B65: 7 | C65: SEMINOVOS | D65: Tesouraria | E65: Financeiro | F65: Patricia/ Regicléssia | G65: =$O65&"º dia útil - "&TEXT(_xlfn.XLOOKUP($A$1&"|"&$O65,ListBox!$H:$H,ListBox!$A:$A,0,0),"DD/MMM") -> 3º dia útil - 05/out | H65: 0.75 | O65: 3
B66: 8 | C66: SEMINOVOS | D66: Patrimômio (movimentação) | E66: Patrimonio | F66: Gabriely | G66: =$O66&"º dia útil - "&TEXT(_xlfn.XLOOKUP($A$1&"|"&$O66,ListBox!$H:$H,ListBox!$A:$A,0,0),"DD/MMM") -> 3º dia útil - 05/out | H66: 0.75 | O66: 3
B67: 9 | C67: SEMINOVOS | D67: Tributos | E67: Fiscal | F67: Joyce | G67: =$O67&"º dia útil - "&TEXT(_xlfn.XLOOKUP($A$1&"|"&$O67,ListBox!$H:$H,ListBox!$A:$A,0,0),"DD/MMM") -> 7º dia útil - 09/out | H67: 0.75 | O67: 7
B68: 1 | C68: CAMINHÕES MT | D68: Folha de Pagamento | E68: DP | F68: Marta/ Elizete | G68: =$O68&"º dia útil - "&TEXT(_xlfn.XLOOKUP($A$1&"|"&$O68,ListBox!$H:$H,ListBox!$A:$A,0,0),"DD/MMM") -> 4º dia útil - 06/out | H68: 0.75 | O68: 4
B69: 2 | C69: CAMINHÕES MT | D69: Compras | E69: Suprimentos | F69: Kaio/Erica | G69: 46295 | H69: 0.75 | O69: 1
B70: 3 | C70: CAMINHÕES MT | D70: Vendas | E70: Faturamento | F70: Marcus/ Fabiana | G70: 46295 | H70: 0.75 | O70: 1
B71: 1 | C71: CAMINHÕES MT | D71: Folha de Pagamento | E71: DP | F71: Marta/ Elizete | G71: =$O71&"º dia útil - "&TEXT(_xlfn.XLOOKUP($A$1&"|"&$O71,ListBox!$H:$H,ListBox!$A:$A,0,0),"DD/MMM") -> 4º dia útil - 06/out | H71: 0.75 | O71: 4
B72: 2 | C72: CAMINHÕES MT | D72: Compras | E72: Suprimentos | F72: Kaio/Erica | G72: 46295 | H72: 0.75 | O72: 1
B73: 3 | C73: CAMINHÕES MT | D73: Vendas | E73: Faturamento | F73: Marcus/ Fabiana | G73: 46295 | H73: 0.75 | O73: 1
B74: 4 | C74: CAMINHÕES MT | D74: Estoque | E74: Estoque | F74: Marcus | G74: 46295 | H74: 0.75 | O74: 1
B75: 5 | C75: CAMINHÕES MT | D75: Contas a Pagar | E75: Financeiro | F75: Patricia/ Regiclessia | G75: =$O75&"º dia útil - "&TEXT(_xlfn.XLOOKUP($A$1&"|"&$O75,ListBox!$H:$H,ListBox!$A:$A,0,0),"DD/MMM") -> 3º dia útil - 05/out | H75: 0.75 | O75: 3
B76: 6 | C76: CAMINHÕES MT | D76: Contas a Receber | E76: Financeiro | F76: Patricia/Luciene | G76: =$O76&"º dia útil - "&TEXT(_xlfn.XLOOKUP($A$1&"|"&$O76,ListBox!$H:$H,ListBox!$A:$A,0,0),"DD/MMM") -> 3º dia útil - 05/out | H76: 0.75 | O76: 3
B77: 7 | C77: CAMINHÕES MT | D77: Tesouraria | E77: Financeiro | F77: Patricia/ Regicléssia | G77: =$O77&"º dia útil - "&TEXT(_xlfn.XLOOKUP($A$1&"|"&$O77,ListBox!$H:$H,ListBox!$A:$A,0,0),"DD/MMM") -> 3º dia útil - 05/out | H77: 0.75 | O77: 3
B78: 8 | C78: CAMINHÕES MT | D78: Patrimômio (movimentação) | E78: Patrimonio | F78: Gabriely | G78: =$O78&"º dia útil - "&TEXT(_xlfn.XLOOKUP($A$1&"|"&$O78,ListBox!$H:$H,ListBox!$A:$A,0,0),"DD/MMM") -> 3º dia útil - 05/out | H78: 0.75 | O78: 3
B79: 9 | C79: CAMINHÕES MT | D79: Tributos | E79: Fiscal | F79: Joyce | G79: =$O79&"º dia útil - "&TEXT(_xlfn.XLOOKUP($A$1&"|"&$O79,ListBox!$H:$H,ListBox!$A:$A,0,0),"DD/MMM") -> 7º dia útil - 09/out | H79: 0.75 | O79: 7
B80: 9 | C80: LOGISTICA | D80: Contábil/Integração | E80: Contábil | F80: Joyce/ Equipe Contábil | G80: =$O80&"º dia útil - "&TEXT(_xlfn.XLOOKUP($A$1&"|"&$O80,ListBox!$H:$H,ListBox!$A:$A,0,0),"DD/MMM") -> 9º dia útil - 14/out | H80: 0.75 | O80: 9
B81: 9 | C81: BIOMASSA | D81: Contábil/Integração | E81: Contábil | F81: Joyce/ Equipe Contábil | G81: =$O81&"º dia útil - "&TEXT(_xlfn.XLOOKUP($A$1&"|"&$O81,ListBox!$H:$H,ListBox!$A:$A,0,0),"DD/MMM") -> 9º dia útil - 14/out | H81: 0.75 | O81: 9
B82: 9 | C82: COMBER SA | D82: Contábil/Integração | E82: Contábil | F82: Joyce/ Equipe Contábil | G82: =$O82&"º dia útil - "&TEXT(_xlfn.XLOOKUP($A$1&"|"&$O82,ListBox!$H:$H,ListBox!$A:$A,0,0),"DD/MMM") -> 9º dia útil - 14/out | H82: 0.75 | O82: 9
B83: 9 | C83: FLORESTAL TO | D83: Contábil/Integração | E83: Contábil | F83: Joyce/ Equipe Contábil | G83: =$O83&"º dia útil - "&TEXT(_xlfn.XLOOKUP($A$1&"|"&$O83,ListBox!$H:$H,ListBox!$A:$A,0,0),"DD/MMM") -> 9º dia útil - 14/out | H83: 0.75 | O83: 9
B84: 9 | C84: SEMINOVOS | D84: Contábil/Integração | E84: Contábil | F84: Joyce/ Equipe Contábil | G84: =$O84&"º dia útil - "&TEXT(_xlfn.XLOOKUP($A$1&"|"&$O84,ListBox!$H:$H,ListBox!$A:$A,0,0),"DD/MMM") -> 9º dia útil - 14/out | H84: 0.75 | O84: 9
B85: 9 | C85: CAMINHÕES MT | D85: Contábil/Integração | E85: Contábil | F85: Joyce/ Equipe Contábil | G85: =$O85&"º dia útil - "&TEXT(_xlfn.XLOOKUP($A$1&"|"&$O85,ListBox!$H:$H,ListBox!$A:$A,0,0),"DD/MMM") -> 9º dia útil - 14/out | H85: 0.75 | O85: 9
B86: 9 | C86: LOGISTICA | D86: Balancete Fechado | E86: Contábil | F86: Joyce/ Equipe Contábil | G86: =$O86&"º dia útil - "&TEXT(_xlfn.XLOOKUP($A$1&"|"&$O86,ListBox!$H:$H,ListBox!$A:$A,0,0),"DD/MMM") -> 15º dia útil - 22/out | H86: 0.75 | O86: 15
... B91: 9 | C91: CAMINHÕES MT | D91: Balancete Fechado | E91: Contábil | F91: Joyce/ Equipe Contábil | G91: =$O91&"º dia útil - "&TEXT(_xlfn.XLOOKUP($A$1&"|"&$O91,ListBox!$H:$H,ListBox!$A:$A,0,0),"DD/MMM") -> 15º dia útil - 22/out | H91: 0.75 | O91: 15
B92: 1 | C92: LOCAÇÕES | D92: Compras | E92: Suprimentos | F92: Kaio/Erica | G92: 46295 | H92: 0.75 | O92: 1
B93: 2 | C93: LOCAÇÕES | D93: Vendas | E93: Faturamento | F93: Marcus/ Fabiana | G93: 46295 | H93: 0.75 | O93: 1
B94: 3 | C94: LOCAÇÕES | D94: Estoque | E94: Estoque | F94: Marcus | G94: 46295 | H94: 0.75 | O94: 1
B95: 4 | C95: LOCAÇÕES | D95: Contas a Pagar | E95: Financeiro | F95: Patricia/ Regiclessia | G95: =$O95&"º dia útil - "&TEXT(_xlfn.XLOOKUP($A$1&"|"&$O95,ListBox!$H:$H,ListBox!$A:$A,0,0),"DD/MMM") -> 3º dia útil - 05/out | H95: 0.75 | O95: 3
B96: 5 | C96: LOCAÇÕES | D96: Contas a Receber | E96: Financeiro | F96: Patricia/Luciene | G96: =$O96&"º dia útil - "&TEXT(_xlfn.XLOOKUP($A$1&"|"&$O96,ListBox!$H:$H,ListBox!$A:$A,0,0),"DD/MMM") -> 3º dia útil - 05/out | H96: 0.75 | O96: 3
B97: 6 | C97: LOCAÇÕES | D97: Tesouraria | E97: Financeiro | F97: Patricia/ Regicléssia | G97: =$O97&"º dia útil - "&TEXT(_xlfn.XLOOKUP($A$1&"|"&$O97,ListBox!$H:$H,ListBox!$A:$A,0,0),"DD/MMM") -> 3º dia útil - 05/out | H97: 0.75 | O97: 3
B98: 7 | C98: LOCAÇÕES | D98: Patrimômio (movimentação) | E98: Patrimonio | F98: Gabriely | G98: =$O98&"º dia útil - "&TEXT(_xlfn.XLOOKUP($A$1&"|"&$O98,ListBox!$H:$H,ListBox!$A:$A,0,0),"DD/MMM") -> 3º dia útil - 05/out | H98: 0.75 | O98: 3
B99: 18 | C99: GRUNE | D99: Patrimômio (movimentação) | E99: Patrimonio | F99: Gabriely | G99: =$O99&"º dia útil - "&TEXT(_xlfn.XLOOKUP($A$1&"|"&$O99,ListBox!$H:$H,ListBox!$A:$A,0,0),"DD/MMM") -> 3º dia útil - 05/out | H99: 0.75 | O99: 3
B100: 8 | C100: LOCAÇÕES | D100: Tributos | E100: Fiscal | F100: Joyce | G100: =$O100&"º dia útil - "&TEXT(_xlfn.XLOOKUP($A$1&"|"&$O100,ListBox!$H:$H,ListBox!$A:$A,0,0),"DD/MMM") -> 7º dia útil - 09/out | H100: 0.75 | O100: 7
B101: 7 | C101: IFL PATRIMONIAL | D101: Tesouraria | E101: Financeiro | F101: Jamile | G101: =$O101&"º dia útil - "&TEXT(_xlfn.XLOOKUP($A$1&"|"&$O101,ListBox!$H:$H,ListBox!$A:$A,0,0),"DD/MMM") -> 3º dia útil - 05/out | H101: 0.75 | O101: 3
B102: 7 | C102: IFL PARTICIPAÇÕES | D102: Tesouraria | E102: Financeiro | F102: Patricia/ Regicléssia | G102: =$O102&"º dia útil - "&TEXT(_xlfn.XLOOKUP($A$1&"|"&$O102,ListBox!$H:$H,ListBox!$A:$A,0,0),"DD/MMM") -> 3º dia útil - 05/out | H102: 0.75 | O102: 3
B103: 7 | C103: FT4 COMELLI HOLDING | D103: Tesouraria | E103: Financeiro | F103: Jamile | G103: =$O103&"º dia útil - "&TEXT(_xlfn.XLOOKUP($A$1&"|"&$O103,ListBox!$H:$H,ListBox!$A:$A,0,0),"DD/MMM") -> 3º dia útil - 05/out | H103: 0.75 | O103: 3
B104: 7 | C104: LC COMELLI HOLDING | D104: Tesouraria | E104: Financeiro | F104: Jamile | G104: =$O104&"º dia útil - "&TEXT(_xlfn.XLOOKUP($A$1&"|"&$O104,ListBox!$H:$H,ListBox!$A:$A,0,0),"DD/MMM") -> 3º dia útil - 05/out | H104: 0.75 | O104: 3
B105: 7 | C105: COMELLI PARTICIPAÇÕES | D105: Tesouraria | E105: Financeiro | F105: Jamile | G105: =$O105&"º dia útil - "&TEXT(_xlfn.XLOOKUP($A$1&"|"&$O105,ListBox!$H:$H,ListBox!$A:$A,0,0),"DD/MMM") -> 3º dia útil - 05/out | H105: 0.75 | O105: 3
B106: 7 | C106: IFL PATRIMONIAL | D106: Patrimômio (movimentação) | E106: Financeiro | F106: Jamile | G106: =$O106&"º dia útil - "&TEXT(_xlfn.XLOOKUP($A$1&"|"&$O106,ListBox!$H:$H,ListBox!$A:$A,0,0),"DD/MMM") -> 3º dia útil - 05/out | H106: 0.75 | O106: 3
C107: COMELLI PARTICIPAÇÕES | D107: Patrimômio (movimentação) | E107: Financeiro | F107: Jamile | G107: =$O107&"º dia útil - "&TEXT(_xlfn.XLOOKUP($A$1&"|"&$O107,ListBox!$H:$H,ListBox!$A:$A,0,0),"DD/MMM") -> 3º dia útil - 05/out | H107: 0.75 | O107: 3
...

Sheet HOLDING
B5: CRONOGRAMA FECHAMENTO - JUNHO
B7: Nº | C7: ATIVIDADES | D7: AREA | E7: IFL COMELLI PARTICIPACOES LTDA | F7: IFL COMELLI PATRIMONIAL LTDA | G7: FT4 COMELLI HOLDING LTDA | H7: COMELLI PARTICIPACOES LTDA | I7: Responsavel | J7: Dia Maximo | K7: Horario Maximo | M7: Entregue em | N7: Horário entrega
B8: 1 | C8: Folha de Pagamento | D8: DP
B10: 2 | C10: Compras | D10: Suprimentos
B12: 3 | C12: Vendas | D12: Faturamento
B14: 4 | C14: Estoque | D14: Estoque | E14: OK | F14: OK | G14: OK | H14: OK | I14: Maria | M14: 45932 | N14: 0.81597222
B16: 5 | C16: Contas a Pagar | D16: Financeiro
B18: 6 | C18: Contas a Receber | D18: Financeiro
B20: 7 | C20: Tesouraria | D20: Financeiro | E20: ok | F20: ok | H20: ok | M20: 45813 | N20: 0.54166667
B22: 8 | C22: Patrimômio (movimentação) | D22: Patrimonio | E22: Sem movimento | F22: OK | G22: Sem movimento | H22: Sem movimento | I22: GUILHERME GUEDES | J22: 45933 | K22: 0.75 | M22: 45719 | N22: 0.86527778
B24: 9 | C24: Tributos | D24: Fiscal
B26: * A GERENCIA DE CADA ÁREA DEVERÁ GARANTIR O FECHAMENTO DO CRONOGRAMA NOS DIAS E HORÁRIOS FIXADOS

Sheet ListBox
A1: Data | B1: Dia da semana | C1: Dia da semana (texto) | D1: Feriado | E1: d.u. (S/N) | F1: dia util | G1: Semana | H1: Chave | J1: Data | K1: Feriado / Ponto Facultativo | L1: Tipo
A2: 46023 | B2: =WEEKDAY(A2,1) -> 5 | C2: =TEXT(B2,"ddddd") -> quinta-feira | D2: =IF(_xlfn.XLOOKUP(A2,J:J,J:J,0,0)=A2,"Sim","") -> Sim | E2: =IF(OR(B2=1,B2=7,D2<>""),"Não","Sim") -> Não | F2: =IF(E2="Sim", COUNTIFS($E$2:E2, "Sim", $A$2:A2, ">="&DATE(YEAR(A2), MONTH(A2), 1)), "") | G2: =WEEKNUM(A2) -> 1 | H2: =IF(F2="","",MONTH(A2)&"|"&F2) | J2: 46023 | K2: Confraternização Universal | L2: Nacional
A3: =A2+1 -> 46024 | B3: =WEEKDAY(A3,1) -> 6 | C3: =TEXT(B3,"ddddd") -> sexta-feira | D3: =IF(_xlfn.XLOOKUP(A3,J:J,J:J,0,0)=A3,"Sim","") | E3: =IF(OR(B3=1,B3=7,D3<>""),"Não","Sim") -> Sim | F3: =IF(E3="Sim", COUNTIFS($E$2:E3, "Sim", $A$2:A3, ">="&DATE(YEAR(A3), MONTH(A3), 1)), "") -> 1 | G3: =WEEKNUM(A3) -> 1 | H3: =IF(F3="","",MONTH(A3)&"|"&F3) -> 1|1 | J3: 46042 | K3: São Sebastião (Padroeiro da Cidade) | L3: Municipal
A4: =A3+1 -> 46025 | B4: =WEEKDAY(A4,1) -> 7 | C4: =TEXT(B4,"ddddd") -> sábado | D4: =IF(_xlfn.XLOOKUP(A4,J:J,J:J,0,0)=A4,"Sim","") | E4: =IF(OR(B4=1,B4=7,D4<>""),"Não","Sim") -> Não | F4: =IF(E4="Sim", COUNTIFS($E$2:E4, "Sim", $A$2:A4, ">="&DATE(YEAR(A4), MONTH(A4), 1)), "") | G4: =WEEKNUM(A4) -> 1 | H4: =IF(F4="","",MONTH(A4)&"|"&F4) | J4: 46069 | K4: Carnaval | L4: Ponto Facultativo
A5: =A4+1 -> 46026 | B5: =WEEKDAY(A5,1) -> 1 | C5: =TEXT(B5,"ddddd") -> domingo | D5: =IF(_xlfn.XLOOKUP(A5,J:J,J:J,0,0)=A5,"Sim","") | E5: =IF(OR(B5=1,B5=7,D5<>""),"Não","Sim") -> Não | F5: =IF(E5="Sim", COUNTIFS($E$2:E5, "Sim", $A$2:A5, ">="&DATE(YEAR(A5), MONTH(A5), 1)), "") | G5: =WEEKNUM(A5) -> 2 | H5: =IF(F5="","",MONTH(A5)&"|"&F5) | J5: 46070 | K5: Carnaval | L5: Ponto Facultativo
A6: =A5+1 -> 46027 | B6: =WEEKDAY(A6,1) -> 2 | C6: =TEXT(B6,"ddddd") -> segunda-feira | D6: =IF(_xlfn.XLOOKUP(A6,J:J,J:J,0,0)=A6,"Sim","") | E6: =IF(OR(B6=1,B6=7,D6<>""),"Não","Sim") -> Sim | F6: =IF(E6="Sim", COUNTIFS($E$2:E6, "Sim", $A$2:A6, ">="&DATE(YEAR(A6), MONTH(A6), 1)), "") -> 2 | G6: =WEEKNUM(A6) -> 2 | H6: =IF(F6="","",MONTH(A6)&"|"&F6) -> 1|2 | J6: 46115 | K6: Paixão de Cristo (Sexta-feira Santa) | L6: Nacional
A7: =A6+1 -> 46028 | B7: =WEEKDAY(A7,1) -> 3 | C7: =TEXT(B7,"ddddd") -> terça-feira | D7: =IF(_xlfn.XLOOKUP(A7,J:J,J:J,0,0)=A7,"Sim","") | E7: =IF(OR(B7=1,B7=7,D7<>""),"Não","Sim") -> Sim | F7: =IF(E7="Sim", COUNTIFS($E$2:E7, "Sim", $A$2:A7, ">="&DATE(YEAR(A7), MONTH(A7), 1)), "") -> 3 | G7: =WEEKNUM(A7) -> 2 | H7: =IF(F7="","",MONTH(A7)&"|"&F7) -> 1|3 | J7: 46133 | K7: Tiradentes | L7: Nacional
A8: =A7+1 -> 46029 | B8: =WEEKDAY(A8,1) -> 4 | C8: =TEXT(B8,"ddddd") -> quarta-feira | D8: =IF(_xlfn.XLOOKUP(A8,J:J,J:J,0,0)=A8,"Sim","") | E8: =IF(OR(B8=1,B8=7,D8<>""),"Não","Sim") -> Sim | F8: =IF(E8="Sim", COUNTIFS($E$2:E8, "Sim", $A$2:A8, ">="&DATE(YEAR(A8), MONTH(A8), 1)), "") -> 4 | G8: =WEEKNUM(A8) -> 2 | H8: =IF(F8="","",MONTH(A8)&"|"&F8) -> 1|4 | J8: 46143 | K8: Dia do Trabalho | L8: Nacional
A9: =A8+1 -> 46030 | B9: =WEEKDAY(A9,1) -> 5 | C9: =TEXT(B9,"ddddd") -> quinta-feira | D9: =IF(_xlfn.XLOOKUP(A9,J:J,J:J,0,0)=A9,"Sim","") | E9: =IF(OR(B9=1,B9=7,D9<>""),"Não","Sim") -> Sim | F9: =IF(E9="Sim", COUNTIFS($E$2:E9, "Sim", $A$2:A9, ">="&DATE(YEAR(A9), MONTH(A9), 1)), "") -> 5 | G9: =WEEKNUM(A9) -> 2 | H9: =IF(F9="","",MONTH(A9)&"|"&F9) -> 1|5 | J9: 46229 | K9: Fundação da Cidade de Goiás | L9: Estadual (Facultativo)
A10: =A9+1 -> 46031 | B10: =WEEKDAY(A10,1) -> 6 | C10: =TEXT(B10,"ddddd") -> sexta-feira | D10: =IF(_xlfn.XLOOKUP(A10,J:J,J:J,0,0)=A10,"Sim","") | E10: =IF(OR(B10=1,B10=7,D10<>""),"Não","Sim") -> Sim | F10: =IF(E10="Sim", COUNTIFS($E$2:E10, "Sim", $A$2:A10, ">="&DATE(YEAR(A10), MONTH(A10), 1)), "") -> 6 | G10: =WEEKNUM(A10) -> 2 | H10: =IF(F10="","",MONTH(A10)&"|"&F10) -> 1|6 | K10: Aniversário de Rio Verde | L10: Municipal
A11: =A10+1 -> 46032 | B11: =WEEKDAY(A11,1) -> 7 | C11: =TEXT(B11,"ddddd") -> sábado | D11: =IF(_xlfn.XLOOKUP(A11,J:J,J:J,0,0)=A11,"Sim","") | E11: =IF(OR(B11=1,B11=7,D11<>""),"Não","Sim") -> Não | F11: =IF(E11="Sim", COUNTIFS($E$2:E11, "Sim", $A$2:A11, ">="&DATE(YEAR(A11), MONTH(A11), 1)), "") | G11: =WEEKNUM(A11) -> 2 | H11: =IF(F11="","",MONTH(A11)&"|"&F11) | J11: 46272 | K11: Independência do Brasil | L11: Nacional
A12: =A11+1 -> 46033 | B12: =WEEKDAY(A12,1) -> 1 | C12: =TEXT(B12,"ddddd") -> domingo | D12: =IF(_xlfn.XLOOKUP(A12,J:J,J:J,0,0)=A12,"Sim","") | E12: =IF(OR(B12=1,B12=7,D12<>""),"Não","Sim") -> Não | F12: =IF(E12="Sim", COUNTIFS($E$2:E12, "Sim", $A$2:A12, ">="&DATE(YEAR(A12), MONTH(A12), 1)), "") | G12: =WEEKNUM(A12) -> 3 | H12: =IF(F12="","",MONTH(A12)&"|"&F12) | J12: 46307 | K12: Nossa Senhora Aparecida | L12: Nacional
A13: =A12+1 -> 46034 | B13: =WEEKDAY(A13,1) -> 2 | C13: =TEXT(B13,"ddddd") -> segunda-feira | D13: =IF(_xlfn.XLOOKUP(A13,J:J,J:J,0,0)=A13,"Sim","") | E13: =IF(OR(B13=1,B13=7,D13<>""),"Não","Sim") -> Sim | F13: =IF(E13="Sim", COUNTIFS($E$2:E13, "Sim", $A$2:A13, ">="&DATE(YEAR(A13), MONTH(A13), 1)), "") -> 7 | G13: =WEEKNUM(A13) -> 3 | H13: =IF(F13="","",MONTH(A13)&"|"&F13) -> 1|7 | J13: 46319 | K13: Lançamento da Pedra Fundamental de Goiânia | L13: Estadual (Facultativo)
A14: =A13+1 -> 46035 | B14: =WEEKDAY(A14,1) -> 3 | C14: =TEXT(B14,"ddddd") -> terça-feira | D14: =IF(_xlfn.XLOOKUP(A14,J:J,J:J,0,0)=A14,"Sim","") | E14: =IF(OR(B14=1,B14=7,D14<>""),"Não","Sim") -> Sim | F14: =IF(E14="Sim", COUNTIFS($E$2:E14, "Sim", $A$2:A14, ">="&DATE(YEAR(A14), MONTH(A14), 1)), "") -> 8 | G14: =WEEKNUM(A14) -> 3 | H14: =IF(F14="","",MONTH(A14)&"|"&F14) -> 1|8 | J14: 46323 | K14: Dia do Servidor Público | L14: Ponto Facultativo
A15: =A14+1 -> 46036 | B15: =WEEKDAY(A15,1) -> 4 | C15: =TEXT(B15,"ddddd") -> quarta-feira | D15: =IF(_xlfn.XLOOKUP(A15,J:J,J:J,0,0)=A15,"Sim","") | E15: =IF(OR(B15=1,B15=7,D15<>""),"Não","Sim") -> Sim | F15: =IF(E15="Sim", COUNTIFS($E$2:E15, "Sim", $A$2:A15, ">="&DATE(YEAR(A15), MONTH(A15), 1)), "") -> 9 | G15: =WEEKNUM(A15) -> 3 | H15: =IF(F15="","",MONTH(A15)&"|"&F15) -> 1|9 | J15: 46328 | K15: Finados | L15: Nacional
A16: =A15+1 -> 46037 | B16: =WEEKDAY(A16,1) -> 5 | C16: =TEXT(B16,"ddddd") -> quinta-feira | D16: =IF(_xlfn.XLOOKUP(A16,J:J,J:J,0,0)=A16,"Sim","") | E16: =IF(OR(B16=1,B16=7,D16<>""),"Não","Sim") -> Sim | F16: =IF(E16="Sim", COUNTIFS($E$2:E16, "Sim", $A$2:A16, ">="&DATE(YEAR(A16), MONTH(A16), 1)), "") -> 10 | G16: =WEEKNUM(A16) -> 3 | H16: =IF(F16="","",MONTH(A16)&"|"&F16) -> 1|10 | J16: 46341 | K16: Proclamação da República | L16: Nacional
A17: =A16+1 -> 46038 | B17: =WEEKDAY(A17,1) -> 6 | C17: =TEXT(B17,"ddddd") -> sexta-feira | D17: =IF(_xlfn.XLOOKUP(A17,J:J,J:J,0,0)=A17,"Sim","") | E17: =IF(OR(B17=1,B17=7,D17<>""),"Não","Sim") -> Sim | F17: =IF(E17="Sim", COUNTIFS($E$2:E17, "Sim", $A$2:A17, ">="&DATE(YEAR(A17), MONTH(A17), 1)), "") -> 11 | G17: =WEEKNUM(A17) -> 3 | H17: =IF(F17="","",MONTH(A17)&"|"&F17) -> 1|11 | J17: 46346 | K17: Dia de Zumbi e da Consciência Negra | L17: Nacional
A18: =A17+1 -> 46039 | B18: =WEEKDAY(A18,1) -> 7 | C18: =TEXT(B18,"ddddd") -> sábado | D18: =IF(_xlfn.XLOOKUP(A18,J:J,J:J,0,0)=A18,"Sim","") | E18: =IF(OR(B18=1,B18=7,D18<>""),"Não","Sim") -> Não | F18: =IF(E18="Sim", COUNTIFS($E$2:E18, "Sim", $A$2:A18, ">="&DATE(YEAR(A18), MONTH(A18), 1)), "") | G18: =WEEKNUM(A18) -> 3 | H18: =IF(F18="","",MONTH(A18)&"|"&F18) | J18: 46381 | K18: Natal | L18: Nacional
A19: =A18+1 -> 46040 | B19: =WEEKDAY(A19,1) -> 1 | C19: =TEXT(B19,"ddddd") -> domingo | D19: =IF(_xlfn.XLOOKUP(A19,J:J,J:J,0,0)=A19,"Sim","") | E19: =IF(OR(B19=1,B19=7,D19<>""),"Não","Sim") -> Não | F19: =IF(E19="Sim", COUNTIFS($E$2:E19, "Sim", $A$2:A19, ">="&DATE(YEAR(A19), MONTH(A19), 1)), "") | G19: =WEEKNUM(A19) -> 4 | H19: =IF(F19="","",MONTH(A19)&"|"&F19)
A20: =A19+1 -> 46041 | B20: =WEEKDAY(A20,1) -> 2 | C20: =TEXT(B20,"ddddd") -> segunda-feira | D20: =IF(_xlfn.XLOOKUP(A20,J:J,J:J,0,0)=A20,"Sim","") | E20: =IF(OR(B20=1,B20=7,D20<>""),"Não","Sim") -> Sim | F20: =IF(E20="Sim", COUNTIFS($E$2:E20, "Sim", $A$2:A20, ">="&DATE(YEAR(A20), MONTH(A20), 1)), "") -> 12 | G20: =WEEKNUM(A20) -> 4 | H20: =IF(F20="","",MONTH(A20)&"|"&F20) -> 1|12
A21: =A20+1 -> 46042 | B21: =WEEKDAY(A21,1) -> 3 | C21: =TEXT(B21,"ddddd") -> terça-feira | D21: =IF(_xlfn.XLOOKUP(A21,J:J,J:J,0,0)=A21,"Sim","") -> Sim | E21: =IF(OR(B21=1,B21=7,D21<>""),"Não","Sim") -> Não | F21: =IF(E21="Sim", COUNTIFS($E$2:E21, "Sim", $A$2:A21, ">="&DATE(YEAR(A21), MONTH(A21), 1)), "") | G21: =WEEKNUM(A21) -> 4 | H21: =IF(F21="","",MONTH(A21)&"|"&F21)
A22: =A21+1 -> 46043 | B22: =WEEKDAY(A22,1) -> 4 | C22: =TEXT(B22,"ddddd") -> quarta-feira | D22: =IF(_xlfn.XLOOKUP(A22,J:J,J:J,0,0)=A22,"Sim","") | E22: =IF(OR(B22=1,B22=7,D22<>""),"Não","Sim") -> Sim | F22: =IF(E22="Sim", COUNTIFS($E$2:E22, "Sim", $A$2:A22, ">="&DATE(YEAR(A22), MONTH(A22), 1)), "") -> 13 | G22: =WEEKNUM(A22) -> 4 | H22: =IF(F22="","",MONTH(A22)&"|"&F22) -> 1|13
A23: =A22+1 -> 46044 | B23: =WEEKDAY(A23,1) -> 5 | C23: =TEXT(B23,"ddddd") -> quinta-feira | D23: =IF(_xlfn.XLOOKUP(A23,J:J,J:J,0,0)=A23,"Sim","") | E23: =IF(OR(B23=1,B23=7,D23<>""),"Não","Sim") -> Sim | F23: =IF(E23="Sim", COUNTIFS($E$2:E23, "Sim", $A$2:A23, ">="&DATE(YEAR(A23), MONTH(A23), 1)), "") -> 14 | G23: =WEEKNUM(A23) -> 4 | H23: =IF(F23="","",MONTH(A23)&"|"&F23) -> 1|14
A24: =A23+1 -> 46045 | B24: =WEEKDAY(A24,1) -> 6 | C24: =TEXT(B24,"ddddd") -> sexta-feira | D24: =IF(_xlfn.XLOOKUP(A24,J:J,J:J,0,0)=A24,"Sim","") | E24: =IF(OR(B24=1,B24=7,D24<>""),"Não","Sim") -> Sim | F24: =IF(E24="Sim", COUNTIFS($E$2:E24, "Sim", $A$2:A24, ">="&DATE(YEAR(A24), MONTH(A24), 1)), "") -> 15 | G24: =WEEKNUM(A24) -> 4 | H24: =IF(F24="","",MONTH(A24)&"|"&F24) -> 1|15
A25: =A24+1 -> 46046 | B25: =WEEKDAY(A25,1) -> 7 | C25: =TEXT(B25,"ddddd") -> sábado | D25: =IF(_xlfn.XLOOKUP(A25,J:J,J:J,0,0)=A25,"Sim","") | E25: =IF(OR(B25=1,B25=7,D25<>""),"Não","Sim") -> Não | F25: =IF(E25="Sim", COUNTIFS($E$2:E25, "Sim", $A$2:A25, ">="&DATE(YEAR(A25), MONTH(A25), 1)), "") | G25: =WEEKNUM(A25) -> 4 | H25: =IF(F25="","",MONTH(A25)&"|"&F25)
A26: =A25+1 -> 46047 | B26: =WEEKDAY(A26,1) -> 1 | C26: =TEXT(B26,"ddddd") -> domingo | D26: =IF(_xlfn.XLOOKUP(A26,J:J,J:J,0,0)=A26,"Sim","") | E26: =IF(OR(B26=1,B26=7,D26<>""),"Não","Sim") -> Não | F26: =IF(E26="Sim", COUNTIFS($E$2:E26, "Sim", $A$2:A26, ">="&DATE(YEAR(A26), MONTH(A26), 1)), "") | G26: =WEEKNUM(A26) -> 5 | H26: =IF(F26="","",MONTH(A26)&"|"&F26)
A27: =A26+1 -> 46048 | B27: =WEEKDAY(A27,1) -> 2 | C27: =TEXT(B27,"ddddd") -> segunda-feira | D27: =IF(_xlfn.XLOOKUP(A27,J:J,J:J,0,0)=A27,"Sim","") | E27: =IF(OR(B27=1,B27=7,D27<>""),"Não","Sim") -> Sim | F27: =IF(E27="Sim", COUNTIFS($E$2:E27, "Sim", $A$2:A27, ">="&DATE(YEAR(A27), MONTH(A27), 1)), "") -> 16 | G27: =WEEKNUM(A27) -> 5 | H27: =IF(F27="","",MONTH(A27)&"|"&F27) -> 1|16
A28: =A27+1 -> 46049 | B28: =WEEKDAY(A28,1) -> 3 | C28: =TEXT(B28,"ddddd") -> terça-feira | D28: =IF(_xlfn.XLOOKUP(A28,J:J,J:J,0,0)=A28,"Sim","") | E28: =IF(OR(B28=1,B28=7,D28<>""),"Não","Sim") -> Sim | F28: =IF(E28="Sim", COUNTIFS($E$2:E28, "Sim", $A$2:A28, ">="&DATE(YEAR(A28), MONTH(A28), 1)), "") -> 17 | G28: =WEEKNUM(A28) -> 5 | H28: =IF(F28="","",MONTH(A28)&"|"&F28) -> 1|17
A29: =A28+1 -> 46050 | B29: =WEEKDAY(A29,1) -> 4 | C29: =TEXT(B29,"ddddd") -> quarta-feira | D29: =IF(_xlfn.XLOOKUP(A29,J:J,J:J,0,0)=A29,"Sim","") | E29: =IF(OR(B29=1,B29=7,D29<>""),"Não","Sim") -> Sim | F29: =IF(E29="Sim", COUNTIFS($E$2:E29, "Sim", $A$2:A29, ">="&DATE(YEAR(A29), MONTH(A29), 1)), "") -> 18 | G29: =WEEKNUM(A29) -> 5 | H29: =IF(F29="","",MONTH(A29)&"|"&F29) -> 1|18
A30: =A29+1 -> 46051 | B30: =WEEKDAY(A30,1) -> 5 | C30: =TEXT(B30,"ddddd") -> quinta-feira | D30: =IF(_xlfn.XLOOKUP(A30,J:J,J:J,0,0)=A30,"Sim","") | E30: =IF(OR(B30=1,B30=7,D30<>""),"Não","Sim") -> Sim | F30: =IF(E30="Sim", COUNTIFS($E$2:E30, "Sim", $A$2:A30, ">="&DATE(YEAR(A30), MONTH(A30), 1)), "") -> 19 | G30: =WEEKNUM(A30) -> 5 | H30: =IF(F30="","",MONTH(A30)&"|"&F30) -> 1|19
... A366: =A365+1 -> 46387 | B366: =WEEKDAY(A366,1) -> 5 | C366: =TEXT(B366,"ddddd") -> quinta-feira | D366: =IF(_xlfn.XLOOKUP(A366,J:J,J:J,0,0)=A366,"Sim","") | E366: =IF(OR(B366=1,B366=7,D366<>""),"Não","Sim") -> Sim | F366: =IF(E366="Sim", COUNTIFS($E$2:E366, "Sim", $A$2:A366, ">="&DATE(YEAR(A366), MONTH(A366), 1)), "") -> 22 | G366: =WEEKNUM(A366) -> 53 | H366: =IF(F366="","",MONTH(A366)&"|"&F366) -> 12|22

Sheet Cronograma Fechamento
B2: ="DETALHAMENTO DAS ENTREGAS · "&_xlfn.TEXTAFTER('Consolidado- Comber'!$B$5,"- ") -> DETALHAMENTO DAS ENTREGAS · SETEMBRO 2026
B3: A gerência de cada área deverá garantir o fechamento das entregas nos dias e horários previstos.
B6: ÁREA | C6: ATIVIDADE | D6: RESPONSÁVEL | E6: EMPRESAS ENVOLVIDAS | F6: ENTREGAS | G6: ATÉ
B7: =$C$33&"º DIA ÚTIL · "&TEXT(_xlfn.XLOOKUP('Consolidado- Comber'!$A$1&"|"&$C$33,ListBox!$H:$H,ListBox!$A:$A,0,0),"dd/mmm")&" · Fechamento das áreas operacionais e validação fiscal" -> 1º DIA ÚTIL · 01/out · Fechamento das áreas operacionais e validação fiscal | F7: =SUM(F8:F12) -> 35 | G7: ='Consolidado- Comber'!$H$8 -> 0.75
B8: Suprimentos | C8: Compras | D8: Marcus · Leânia | E8: Logística · Biomassa · Comber SA · Florestal TO · Seminovos · Caminhões MT · Locações | F8: {=SUMPRODUCT(--(COUNTIFS('Consolidado- Comber'!$C$8:$C$146,$B$33:$B$45,'Consolidado- Comber'!$D$8:$D$146,"Compras",'Consolidado- Comber'!$O$8:$O$146,$C$33)>0))} -> 7 | G8: ='Consolidado- Comber'!$H$8 -> 0.75
B9: Faturamento | C9: Vendas | D9: Marcus · Fabiana | E9: Logística · Biomassa · Comber SA · Florestal TO · Seminovos · Caminhões MT · Locações | F9: {=SUMPRODUCT(--(COUNTIFS('Consolidado- Comber'!$C$8:$C$146,$B$33:$B$45,'Consolidado- Comber'!$D$8:$D$146,"Vendas",'Consolidado- Comber'!$O$8:$O$146,$C$33)>0))} -> 7 | G9: ='Consolidado- Comber'!$H$8 -> 0.75
B10: Estoque | C10: Estoque | D10: Marcus · Simone | E10: Logística · Biomassa · Comber SA · Florestal TO · Seminovos · Caminhões MT · Locações | F10: {=SUMPRODUCT(--(COUNTIFS('Consolidado- Comber'!$C$8:$C$146,$B$33:$B$45,'Consolidado- Comber'!$D$8:$D$146,"Estoque",'Consolidado- Comber'!$O$8:$O$146,$C$33)>0))} -> 7 | G10: ='Consolidado- Comber'!$H$8 -> 0.75
B11: Escrita Fiscal | C11: =B11 -> Escrita Fiscal | D11: Kaio · Erica | E11: Logística · Biomassa · Comber SA · Florestal TO · Seminovos · Caminhões MT · Locações | F11: {=SUMPRODUCT(--(COUNTIFS('Consolidado- Comber'!$C$8:$C$146,$B$33:$B$45,'Consolidado- Comber'!$D$8:$D$146,"Estoque",'Consolidado- Comber'!$O$8:$O$146,$C$33)>0))} -> 7 | G11: ='Consolidado- Comber'!$H$8 -> 0.75
B12: Fiscal | C12: Validação Fiscal | D12: Joyce · Mariana | E12: Logística · Biomassa · Comber SA · Florestal TO · Seminovos · Caminhões MT · Locações | F12: {=SUMPRODUCT(--(COUNTIFS('Consolidado- Comber'!$C$8:$C$146,$B$33:$B$45,'Consolidado- Comber'!$D$8:$D$146,"Validação Fiscal",'Consolidado- Comber'!$O$8:$O$146,$C$33)>0))} -> 7 | G12: ='Consolidado- Comber'!$H$8 -> 0.75
B13: =$C$34&"º DIA ÚTIL · "&TEXT(_xlfn.XLOOKUP('Consolidado- Comber'!$A$1&"|"&$C$34,ListBox!$H:$H,ListBox!$A:$A,0,0),"dd/mmm")&" · Correção dos apontamentos da validação fiscal" -> 2º DIA ÚTIL · 02/out · Correção dos apontamentos da validação fiscal | F13: =SUM(F14:F14) -> 7 | G13: ='Consolidado- Comber'!$H$8 -> 0.75
B14: Fiscal | C14: Iniciar apuração de Tributos | D14: Joyce · Mariana | E14: Logística · Biomassa · Comber SA · Florestal TO · Seminovos · Caminhões MT · Locações | F14: {=SUMPRODUCT(--(COUNTIFS('Consolidado- Comber'!$C$8:$C$146,$B$33:$B$45,'Consolidado- Comber'!$D$8:$D$146,"Correção Validação Fiscal",'Consolidado- Comber'!$O$8:$O$146,$C$34)>0))} -> 7 | G14: ='Consolidado- Comber'!$H$8 -> 0.75
B15: =$C$35&"º DIA ÚTIL · "&TEXT(_xlfn.XLOOKUP('Consolidado- Comber'!$A$1&"|"&$C$35,ListBox!$H:$H,ListBox!$A:$A,0,0),"dd/mmm")&" · Financeiro, tesouraria e patrimônio" -> 3º DIA ÚTIL · 05/out · Financeiro, tesouraria e patrimônio | F15: =SUM(F16:F19) -> 46 | G15: ='Consolidado- Comber'!$H$8 -> 0.75
B16: Financeiro | C16: Contas a Pagar | D16: Patrícia · Regicléssia · Jamile | E16: Operacionais (7) + Holdings (IFL Patrimonial, IFL Participações, FT4, LC Comelli, Comelli Part.) | F16: {=SUMPRODUCT(--(COUNTIFS('Consolidado- Comber'!$C$8:$C$146,$B$33:$B$45,'Consolidado- Comber'!$D$8:$D$146,"Contas a Pagar*",'Consolidado- Comber'!$O$8:$O$146,$C$35)>0))} -> 12 | G16: ='Consolidado- Comber'!$H$8 -> 0.75
B17: Financeiro | C17: Contas a Receber | D17: Patrícia · Luciene · Jamile | E17: Operacionais (7) + Holdings (IFL Patrimonial, IFL Participações, FT4, LC Comelli, Comelli Part.) | F17: {=SUMPRODUCT(--(COUNTIFS('Consolidado- Comber'!$C$8:$C$146,$B$33:$B$45,'Consolidado- Comber'!$D$8:$D$146,"Contas a Receber*",'Consolidado- Comber'!$O$8:$O$146,$C$35)>0))} -> 12 | G17: ='Consolidado- Comber'!$H$8 -> 0.75
B18: Financeiro | C18: Tesouraria | D18: Patrícia · Regicléssia · Jamile | E18: Operacionais (7) + Holdings (IFL Patrimonial, IFL Participações, FT4, LC Comelli, Comelli Part.) | F18: {=SUMPRODUCT(--(COUNTIFS('Consolidado- Comber'!$C$8:$C$146,$B$33:$B$45,'Consolidado- Comber'!$D$8:$D$146,"Tesouraria",'Consolidado- Comber'!$O$8:$O$146,$C$35)>0))} -> 12 | G18: ='Consolidado- Comber'!$H$8 -> 0.75
B19: Patrimônio | C19: Patrimônio (movimentação) | D19: Gabriely · Jamile | E19: Operacionais (7) · Grune · IFL Patrimonial | F19: {=SUMPRODUCT(--(COUNTIFS('Consolidado- Comber'!$C$8:$C$146,$B$33:$B$45,'Consolidado- Comber'!$D$8:$D$146,"Patrimômio*",'Consolidado- Comber'!$O$8:$O$146,$C$35)>0))} -> 10 | G19: ='Consolidado- Comber'!$H$8 -> 0.75
B20: =$C$36&"º DIA ÚTIL · "&TEXT(_xlfn.XLOOKUP('Consolidado- Comber'!$A$1&"|"&$C$36,ListBox!$H:$H,ListBox!$A:$A,0,0),"dd/mmm")&" · Folha de pagamento" -> 4º DIA ÚTIL · 06/out · Folha de pagamento | F20: =SUM(F21:F21) -> 6 | G20: ='Consolidado- Comber'!$H$8 -> 0.75
B21: DP | C21: Folha de Pagamento | D21: Danilo · Elizete | E21: Logística · Biomassa · Comber SA · Florestal TO · Seminovos · Caminhões MT | F21: {=SUMPRODUCT(--(COUNTIFS('Consolidado- Comber'!$C$8:$C$146,$B$33:$B$45,'Consolidado- Comber'!$D$8:$D$146,"Folha de Pagamento",'Consolidado- Comber'!$O$8:$O$146,$C$36)>0))} -> 6 | G21: ='Consolidado- Comber'!$H$8 -> 0.75
B22: =$C$37&"º DIA ÚTIL · "&TEXT(_xlfn.XLOOKUP('Consolidado- Comber'!$A$1&"|"&$C$37,ListBox!$H:$H,ListBox!$A:$A,0,0),"dd/mmm")&" · Apuração de tributos" -> 7º DIA ÚTIL · 09/out · Apuração de tributos | F22: =SUM(F23:F23) -> 7 | G22: ='Consolidado- Comber'!$H$8 -> 0.75
B23: Fiscal | C23: Tributos | D23: Joyce · Mariana | E23: Logística · Biomassa · Comber SA · Florestal TO · Seminovos · Caminhões MT · Locações | F23: {=SUMPRODUCT(--(COUNTIFS('Consolidado- Comber'!$C$8:$C$146,$B$33:$B$45,'Consolidado- Comber'!$D$8:$D$146,"Tributos",'Consolidado- Comber'!$O$8:$O$146,$C$37)>0))} -> 7 | G23: ='Consolidado- Comber'!$H$8 -> 0.75
B24: =$C$38&"º DIA ÚTIL · "&TEXT(_xlfn.XLOOKUP('Consolidado- Comber'!$A$1&"|"&$C$38,ListBox!$H:$H,ListBox!$A:$A,0,0),"dd/mmm")&" · Integração contábil" -> 9º DIA ÚTIL · 14/out · Integração contábil | F24: =SUM(F25:F25) -> 6 | G24: ='Consolidado- Comber'!$H$8 -> 0.75
B25: Contábil | C25: Contábil / Integração | D25: Joyce · Equipe Contábil | E25: Logística · Biomassa · Comber SA · Florestal TO · Seminovos · Caminhões MT | F25: {=SUMPRODUCT(--(COUNTIFS('Consolidado- Comber'!$C$8:$C$146,$B$33:$B$45,'Consolidado- Comber'!$D$8:$D$146,"Contábil/Integração",'Consolidado- Comber'!$O$8:$O$146,$C$38)>0))} -> 6 | G25: ='Consolidado- Comber'!$H$8 -> 0.75
B26: =$C$39&"º DIA ÚTIL · "&TEXT(_xlfn.XLOOKUP('Consolidado- Comber'!$A$1&"|"&$C$39,ListBox!$H:$H,ListBox!$A:$A,0,0),"dd/mmm")&" · Entrega do balancete fechado" -> 15º DIA ÚTIL · 22/out · Entrega do balancete fechado | F26: =SUM(F27:F27) -> 6 | G26: ='Consolidado- Comber'!$H$8 -> 0.75
B27: Contábil | C27: Balancete Fechado | D27: Joyce · Equipe Contábil | E27: Logística · Biomassa · Comber SA · Florestal TO · Seminovos · Caminhões MT | F27: {=SUMPRODUCT(--(COUNTIFS('Consolidado- Comber'!$C$8:$C$146,$B$33:$B$45,'Consolidado- Comber'!$D$8:$D$146,"Balancete Fechado",'Consolidado- Comber'!$O$8:$O$146,$C$39)>0))} -> 6 | G27: ='Consolidado- Comber'!$H$8 -> 0.75
B29: Dias úteis calculados automaticamente pelo calendário (aba ListBox). Alterações de prazo devem ser feitas na aba Consolidado- Comber.
B31: BASE AUXILIAR — não alterar
B32: Empresas do grupo | C32: Dia útil | D32: Áreas
B33: LOGISTICA | C33: 1 | D33: DP
B34: BIOMASSA | C34: 2 | D34: Suprimentos
B35: COMBER SA | C35: 3 | D35: Faturamento
B36: FLORESTAL TO | C36: 4 | D36: Estoque
B37: SEMINOVOS | C37: 7 | D37: Financeiro
B38: CAMINHÕES MT | C38: 9 | D38: Patrimônio
B39: LOCAÇÕES | C39: 15 | D39: Fiscal
B40: GRUNE | D40: Contábil
B41: IFL PATRIMONIAL
B42: IFL PARTICIPAÇÕES
B43: FT4 COMELLI HOLDING
B44: LC COMELLI HOLDING
B45: COMELLI PARTICIPAÇÕES

Sheet Planilha2

Sheet Cards Fechamento
B2: CRONOGRAMA DE FECHAMENTO
B3: ="GRUPO COMBER · "&_xlfn.TEXTAFTER('Consolidado- Comber'!$B$5,"- ") -> GRUPO COMBER · SETEMBRO 2026
B4: A gerência de cada área deverá garantir o fechamento das entregas nos dias e horários previstos.
B6: ULTIMO DIA DO MÊS 09 | F6: ='Cronograma Fechamento'!$C$33&"º DIA ÚTIL" -> 1º DIA ÚTIL | J6: ='Cronograma Fechamento'!$C$34&"º DIA ÚTIL" -> 2º DIA ÚTIL | N6: ='Cronograma Fechamento'!$C$35&"º DIA ÚTIL" -> 3º DIA ÚTIL
B7: 46295 | F7: =TEXT(_xlfn.XLOOKUP('Consolidado- Comber'!$A$1&"|"&'Cronograma Fechamento'!$C$33,ListBox!$H:$H,ListBox!$A:$A,0,0),"dd/mmm") -> 01/out | J7: =TEXT(_xlfn.XLOOKUP('Consolidado- Comber'!$A$1&"|"&'Cronograma Fechamento'!$C$34,ListBox!$H:$H,ListBox!$A:$A,0,0),"dd/mmm") -> 02/out | N7: =TEXT(_xlfn.XLOOKUP('Consolidado- Comber'!$A$1&"|"&'Cronograma Fechamento'!$C$35,ListBox!$H:$H,ListBox!$A:$A,0,0),"dd/mmm") -> 05/out
B8: Fechamento das áreas operacionais | F8: Validação fiscal | J8: Correção da validação fiscal | N8: Financeiro, tesouraria e patrimônio
B9: ='Cronograma Fechamento'!C8 -> Compras | F9: ='Cronograma Fechamento'!C12 -> Validação Fiscal | J9: ='Cronograma Fechamento'!C14 -> Iniciar apuração de Tributos | N9: ='Cronograma Fechamento'!C16 -> Contas a Pagar
B10: ="› "&'Cronograma Fechamento'!D8 -> › Marcus · Leânia | F10: ="› "&'Cronograma Fechamento'!D12 -> › Joyce · Mariana | J10: ="› "&'Cronograma Fechamento'!D14 -> › Joyce · Mariana | N10: ="› "&'Cronograma Fechamento'!D16 -> › Patrícia · Regicléssia · Jamile
B11: ='Cronograma Fechamento'!C9 -> Vendas | N11: ='Cronograma Fechamento'!C17 -> Contas a Receber
B12: ="› "&'Cronograma Fechamento'!D9 -> › Marcus · Fabiana | N12: ="› "&'Cronograma Fechamento'!D17 -> › Patrícia · Luciene · Jamile
B13: ='Cronograma Fechamento'!C10 -> Estoque | N13: ='Cronograma Fechamento'!C18 -> Tesouraria
B14: ="› "&'Cronograma Fechamento'!D10 -> › Marcus · Simone | N14: ="› "&'Cronograma Fechamento'!D18 -> › Patrícia · Regicléssia · Jamile
B15: ='Cronograma Fechamento'!C11 -> Escrita Fiscal | N15: ='Cronograma Fechamento'!C19 -> Patrimônio (movimentação)
B16: ="› "&'Cronograma Fechamento'!D11 -> › Kaio · Erica | N16: ="› "&'Cronograma Fechamento'!D19 -> › Gabriely · Jamile
B17: ="até "&TEXT('Cronograma Fechamento'!$G$7,"hh:mm") -> até 18:00 | F17: ="até "&TEXT('Cronograma Fechamento'!$G$7,"hh:mm") -> até 18:00 | J17: ="até "&TEXT('Cronograma Fechamento'!$G$13,"hh:mm") -> até 18:00 | N17: ="até "&TEXT('Cronograma Fechamento'!$G$15,"hh:mm") -> até 18:00
B19: ='Cronograma Fechamento'!$C$36&"º DIA ÚTIL" -> 4º DIA ÚTIL | F19: ='Cronograma Fechamento'!$C$37&"º DIA ÚTIL" -> 7º DIA ÚTIL | J19: ='Cronograma Fechamento'!$C$38&"º DIA ÚTIL" -> 9º DIA ÚTIL | N19: ='Cronograma Fechamento'!$C$39&"º DIA ÚTIL" -> 15º DIA ÚTIL
B20: =TEXT(_xlfn.XLOOKUP('Consolidado- Comber'!$A$1&"|"&'Cronograma Fechamento'!$C$36,ListBox!$H:$H,ListBox!$A:$A,0,0),"dd/mmm") -> 06/out | F20: =TEXT(_xlfn.XLOOKUP('Consolidado- Comber'!$A$1&"|"&'Cronograma Fechamento'!$C$37,ListBox!$H:$H,ListBox!$A:$A,0,0),"dd/mmm") -> 09/out | J20: =TEXT(_xlfn.XLOOKUP('Consolidado- Comber'!$A$1&"|"&'Cronograma Fechamento'!$C$38,ListBox!$H:$H,ListBox!$A:$A,0,0),"dd/mmm") -> 14/out | N20: =TEXT(_xlfn.XLOOKUP('Consolidado- Comber'!$A$1&"|"&'Cronograma Fechamento'!$C$39,ListBox!$H:$H,ListBox!$A:$A,0,0),"dd/mmm") -> 22/out
B21: Folha de pagamento | F21: Apuração de tributos | J21: Integração contábil | N21: Entrega do balancete fechado
B22: ='Cronograma Fechamento'!C21 -> Folha de Pagamento | F22: ='Cronograma Fechamento'!C23 -> Tributos | J22: ='Cronograma Fechamento'!C25 -> Contábil / Integração | N22: ='Cronograma Fechamento'!C27 -> Balancete Fechado
B23: ="› "&'Cronograma Fechamento'!D21 -> › Danilo · Elizete | F23: ="› "&'Cronograma Fechamento'!D23 -> › Joyce · Mariana | J23: ="› "&'Cronograma Fechamento'!D25 -> › Joyce · Equipe Contábil | N23: ="› "&'Cronograma Fechamento'!D27 -> › Joyce · Equipe Contábil
B27: ="até "&TEXT('Cronograma Fechamento'!$G$20,"hh:mm") -> até 18:00 | F27: ="até "&TEXT('Cronograma Fechamento'!$G$22,"hh:mm") -> até 18:00 | J27: ="até "&TEXT('Cronograma Fechamento'!$G$24,"hh:mm") -> até 18:00 | N27: ="até "&TEXT('Cronograma Fechamento'!$G$26,"hh:mm") -> até 18:00
B29: ="Horário limite de entrega: "&TEXT('Cronograma Fechamento'!$G$7,"hh:mm")&" · "&_xlfn.TEXTAFTER('Consolidado- Comber'!$B$5,"- ") -> Horário limite de entrega: 18:00 · SETEMBRO 2026
B30: Datas calculadas pelo calendário de dias úteis. Fonte: abas Cronograma Fechamento e Consolidado- Comber.

Sheet Planilha3
O3: 5 dias uteis depois do inicio das apurações
C4: 46295 | F4: =C4+1 -> 46296 | I4: =F4+1 -> 46297 | L4: =I4+4 -> 46301 | O4: =I4+7 -> 46304 | R4: =I4+13 -> 46310
C5: Compras | D5: Marcus - Leania | F5: Trava do sistema e validação fiscal | G5: Joyce - Mariana | I5: Início das apurações fiscais | J5: Joyce - Mariana | L5: Folha de pagamento | M5: Danilo - Elizete | O5: Entrega dos impostos apurados (menos PIS/COFINS que precisa da contabilidade finalizada) | P5: Joyce - Mariana | R5: Entrega da contabilidade
C6: Vendas | D6: Marcus - Fabiana | F6: Dia das correções | G6: Compras/Vendas/Estoque/Escrita | I6: Início da contabilidade | J6: Joyce
C7: Estoque | D7: Marcus - Simone | I7: Contas a Pagar | J7: Patricia - Regiclessia
C8: Escrita Fiscal | D8: Kaio - Erica | I8: Contas a Receber | J8: Patricia - Luciene
I9: Tesouraria | J9: Patricia - Regiclessia
I10: Patrimônio | J10: Kaio - Gabriely

Sheet Fluxo no Tempo
B2: ="FLUXO DO FECHAMENTO NO TEMPO · "&_xlfn.TEXTAFTER('Consolidado- Comber'!$B$5,"- ") -> FLUXO DO FECHAMENTO NO TEMPO · SETEMBRO 2026
B3: Linha do tempo por dia útil: cada barra mostra quando a atividade acontece; ◆ marca a entrega (até 18:00). Datas calculadas pelo calendário da aba ListBox.
B5: ATIVIDADE | C5: RESPONSÁVEL | D5: Últ. dia | E5: 1º d.u. | F5: 2º d.u. | G5: 3º d.u. | H5: 4º d.u. | I5: 5º d.u. | J5: 6º d.u. | K5: 7º d.u. | L5: 8º d.u. | M5: 9º d.u. | N5: 10º d.u. | O5: 11º d.u. | P5: 12º d.u. | Q5: 13º d.u.
B6: Data | D6: =WORKDAY(_xlfn.XLOOKUP('Consolidado- Comber'!$A$1&"|"&1,ListBox!$H:$H,ListBox!$A:$A,0,0),-1) -> 46295 | E6: =_xlfn.XLOOKUP('Consolidado- Comber'!$A$1&"|"&1,ListBox!$H:$H,ListBox!$A:$A,0,0) -> 46296 | F6: =_xlfn.XLOOKUP('Consolidado- Comber'!$A$1&"|"&2,ListBox!$H:$H,ListBox!$A:$A,0,0) -> 46297 | G6: =_xlfn.XLOOKUP('Consolidado- Comber'!$A$1&"|"&3,ListBox!$H:$H,ListBox!$A:$A,0,0) -> 46300 | H6: =_xlfn.XLOOKUP('Consolidado- Comber'!$A$1&"|"&4,ListBox!$H:$H,ListBox!$A:$A,0,0) -> 46301 | I6: =_xlfn.XLOOKUP('Consolidado- Comber'!$A$1&"|"&5,ListBox!$H:$H,ListBox!$A:$A,0,0) -> 46302 | J6: =_xlfn.XLOOKUP('Consolidado- Comber'!$A$1&"|"&6,ListBox!$H:$H,ListBox!$A:$A,0,0) -> 46303 | K6: =_xlfn.XLOOKUP('Consolidado- Comber'!$A$1&"|"&7,ListBox!$H:$H,ListBox!$A:$A,0,0) -> 46304 | L6: =_xlfn.XLOOKUP('Consolidado- Comber'!$A$1&"|"&8,ListBox!$H:$H,ListBox!$A:$A,0,0) -> 46308 | M6: =_xlfn.XLOOKUP('Consolidado- Comber'!$A$1&"|"&9,ListBox!$H:$H,ListBox!$A:$A,0,0) -> 46309 | N6: =_xlfn.XLOOKUP('Consolidado- Comber'!$A$1&"|"&10,ListBox!$H:$H,ListBox!$A:$A,0,0) -> 46310 | O6: =_xlfn.XLOOKUP('Consolidado- Comber'!$A$1&"|"&11,ListBox!$H:$H,ListBox!$A:$A,0,0) -> 46311 | P6: =_xlfn.XLOOKUP('Consolidado- Comber'!$A$1&"|"&12,ListBox!$H:$H,ListBox!$A:$A,0,0) -> 46314 | Q6: =_xlfn.XLOOKUP('Consolidado- Comber'!$A$1&"|"&13,ListBox!$H:$H,ListBox!$A:$A,0,0) -> 46315
B7: Dia da semana | D7: =LOWER(TEXT(D6,"ddd")) -> qua | E7: =LOWER(TEXT(E6,"ddd")) -> qui | F7: =LOWER(TEXT(F6,"ddd")) -> sex | G7: =LOWER(TEXT(G6,"ddd")) -> seg | H7: =LOWER(TEXT(H6,"ddd")) -> ter | I7: =LOWER(TEXT(I6,"ddd")) -> qua | J7: =LOWER(TEXT(J6,"ddd")) -> qui | K7: =LOWER(TEXT(K6,"ddd")) -> sex | ... Q7: =LOWER(TEXT(Q6,"ddd")) -> ter
B9: 1 · Fechamento operacional | C9: Entrega das áreas operacionais no último dia do mês
B10: Compras | C10: Marcus · Leânia | D10: ◆
B11: Vendas | C11: Marcus · Fabiana | D11: ◆
B12: Estoque | C12: Marcus · Simone | D12: ◆
B13: Escrita Fiscal | C13: Kaio · Erica | D13: ◆
B14: 2 · Trava, validação fiscal e correções | C14: Sistema travado no 1º d.u.; o time Comber corrige do 1º ao 2º d.u.
B15: Trava do sistema e validação fiscal | C15: Joyce · Mariana | E15: ◆
B16: Correções (time Comber) | C16: Compras · Vendas · Estoque · Escrita | E16: início | F16: ◆
B17: 3 · Financeiro e patrimônio | C17: Entregas no dia em que começam apurações e contabilidade (3º d.u.)
B18: Contas a Pagar | C18: Patrícia · Regicléssia | G18: ◆
B19: Contas a Receber | C19: Patrícia · Luciene | G19: ◆
B20: Tesouraria | C20: Patrícia · Regicléssia | G20: ◆
B21: Patrimônio | C21: Kaio · Gabriely | G21: ◆
B22: 4 · Folha de pagamento
B23: Folha de pagamento | C23: Danilo · Elizete | H23: ◆
B24: 5 · Apurações fiscais | C24: Impostos: entrega 5 dias úteis após o início das apurações
B25: Apuração dos impostos (exceto PIS/COFINS) | C25: Joyce · Mariana | G25: início | L25: ◆
B26: PIS/COFINS finalizado | C26: Joyce · Mariana | O26: ◆
B27: 6 · Contabilidade e balancete fechado | C27: Começa no 3º d.u. e termina com o balancete fechado
B28: Contabilidade → balancete fechado | C28: Joyce · Equipe Contábil | G28: início | Q28: ◆
B30: LEGENDA | C30: ◆ entrega / prazo final (até 18:00) ■ período de execução ··· depende de etapa anterior (sem prazo fixo)
B31: Ordem do fluxo: áreas operacionais (último dia) → trava e validação fiscal (1º d.u.) → correções do time Comber (1º ao 2º d.u.) → apurações, contabilidade e financeiro (3º d.u.) → folha (4º d.u.) → impostos (8º d.u.) → PIS/COFINS (11º d.u.) → balancete fechado (13º d.u.).
B32: Impostos: entrega 5 dias úteis após o início das apurações (3º d.u. + 5 = 8º d.u.). PIS/COFINS finalizado no 11º d.u.
B33: Em paralelo do 3º ao 13º d.u.: apurações fiscais, contabilidade, financeiro/patrimônio (3º d.u.), folha (4º d.u.) e PIS/COFINS (11º d.u.). A contabilidade recebe a folha e os impostos.
B34: Feriados e fins de semana não entram na contagem: as colunas mostram apenas dias úteis.

Sheet Texto E-mail
B2: ="Assunto: Cronograma de Fechamento – "&PROPER(_xlfn.TEXTAFTER('Consolidado- Comber'!$B$5,"- "))&" | Grupo Comber" -> Assunto: Cronograma de Fechamento – Setembro 2026 | Grupo Comber
B5: Prezados,
B6: ="Segue o cronograma de fechamento referente a "&PROPER(_xlfn.TEXTAFTER('Consolidado- Comber'!$B$5,"- "))&". Pedimos atenção especial aos prazos, pois o cumprimento de cada etapa é pré-requisito para a seguinte." -> Segue o cronograma de fechamento referente a Setembro 2026. Pedimos atenção especial aos prazos, pois o cumprimento de cada etapa é pré-requisito para a seguinte.
B9: A gerência de cada área é responsável por garantir o fechamento das suas entregas nos dias e horários previstos. Eventuais impedimentos devem ser comunicados à Controladoria antes do prazo, e não após.
B10: Em anexo, o cronograma completo com as atividades e os respectivos responsáveis.
B12: Atenciosamente,
B13: Controladoria – Grupo Comber
B15: Dica: para o corpo do e-mail, selecione A1:Q31 na aba 'Cards Fechamento', copie e cole como imagem. As datas acima se atualizam sozinhas quando o mês muda.
